setup.py
geofluent/__init__.py
geofluent/cli.py
geofluent/geofluent.py
geofluent/microservice.py
geofluent.egg-info/PKG-INFO
geofluent.egg-info/SOURCES.txt
geofluent.egg-info/dependency_links.txt
geofluent.egg-info/entry_points.txt
geofluent.egg-info/requires.txt
geofluent.egg-info/top_level.txt