Metadata-Version: 1.1
Name: geofluent
Version: 0.2.1
Summary: Unnoficial Python Client to access the GeoFluent API
Home-page: UNKNOWN
Author: Sergio Fernández
Author-email: sergio.fernandez@redlink.co
License: UNKNOWN
Keywords: client api translation geofluent ssix
Platform: any
Classifier: Development Status :: 4 - Beta
Classifier: Intended Audience :: Developers
Classifier: Topic :: Software Development :: Libraries
Classifier: Programming Language :: Python :: 2
Classifier: Programming Language :: Python :: 3
Classifier: Environment :: Console
